fusesoc/config.py
fusesoc/core.py
fusesoc/coremanager.py
fusesoc/edalizer.py
fusesoc/fusesoc.py
fusesoc/librarymanager.py
fusesoc/lockfile.py
fusesoc/main.py
fusesoc/utils.py
fusesoc/version.py
fusesoc/vlnv.py
fusesoc/capi2/core.py
fusesoc/capi2/coredata.py
fusesoc/capi2/coreparser.py
fusesoc/capi2/exprs.py
fusesoc/capi2/generator.py
fusesoc/capi2/inheritance.py
fusesoc/capi2/json_schema.py
fusesoc/filters/autotype.py
fusesoc/filters/coredepsmk.py
fusesoc/filters/custom.py
fusesoc/filters/dot.py
fusesoc/filters/splitlib.py
fusesoc/parser/coreparser.py
fusesoc/provider/git.py
fusesoc/provider/github.py
fusesoc/provider/local.py
fusesoc/provider/opencores.py
fusesoc/provider/provider.py
fusesoc/provider/svn.py
fusesoc/provider/url.py
fusesoc-2.4.3.dist-info/licenses/LICENSE
fusesoc-2.4.3.dist-info/METADATA
fusesoc-2.4.3.dist-info/WHEEL
fusesoc-2.4.3.dist-info/entry_points.txt
fusesoc-2.4.3.dist-info/top_level.txt
fusesoc-2.4.3.dist-info/RECORD
